README.md
setup.py
sem_bump/__init__.py
sem_bump.egg-info/PKG-INFO
sem_bump.egg-info/SOURCES.txt
sem_bump.egg-info/dependency_links.txt
sem_bump.egg-info/entry_points.txt
sem_bump.egg-info/requires.txt
sem_bump.egg-info/top_level.txt